pylarization/__init__.py
pylarization/converters.py
pylarization/elements.py
pylarization/ellipse.py
pylarization/matrices.py
pylarization/polarizations.py
pylarization/vectors.py
pylarization-0.2.1.dist-info/LICENSE.txt
pylarization-0.2.1.dist-info/METADATA
pylarization-0.2.1.dist-info/WHEEL
pylarization-0.2.1.dist-info/top_level.txt
pylarization-0.2.1.dist-info/RECORD
