Metadata-Version: 2.1
Name: pylarization
Version: 0.2.1
Summary: Package for polarization state calculations
Home-page: https://gitlab.com/szuro/pylarization
Author: Robert Szulist
Author-email: r.szulist@gmail.com
License: UNKNOWN
Keywords: polarization light ellipse jones stokes mueller coherency
Platform: UNKNOWN
Classifier: Development Status :: 4 - Beta
Classifier: Intended Audience :: Science/Research
Classifier: Topic :: Scientific/Engineering :: Physics
Classifier: License :: OSI Approved :: MIT License
Classifier: Programming Language :: Python :: 3
Classifier: Programming Language :: Python :: 3.6
Classifier: Programming Language :: Python :: 3.7
Classifier: Programming Language :: Python :: 3.8
Requires-Dist: numpy
